valar_daemon/AppWrapper.py
valar_daemon/Daemon.py
valar_daemon/DaemonConfig.py
valar_daemon/DelegatorContractClient.py
valar_daemon/Logger.py
valar_daemon/NoticeboardClient.py
valar_daemon/PartkeyManager.py
valar_daemon/Timer.py
valar_daemon/ValidatorAdClient.py
valar_daemon/__init__.py
valar_daemon/constants.py
valar_daemon/log_messages_source.yaml
valar_daemon/run_daemon.py
valar_daemon/utils.py
valar_daemon-0.4.0.dist-info/LICENSE
valar_daemon-0.4.0.dist-info/METADATA
valar_daemon-0.4.0.dist-info/WHEEL
valar_daemon-0.4.0.dist-info/RECORD
