Metadata-Version: 2.1
Name: valar_daemon
Version: 0.4.0
Summary: The Valar Daemon is used to automate Validator Manager tasks on the Valar Peer-to-Peer Staking Platform.
Home-page: https://stake.valar.solutions
License: AGPL-3.0-only
Author: Valar Solutions GmbH
Author-email: info@valar.solutions
Requires-Python: >=3.12,<4.0
Classifier: License :: OSI Approved :: GNU Affero General Public License v3
Classifier: Programming Language :: Python :: 3
Classifier: Programming Language :: Python :: 3.12
Requires-Dist: Deprecated (>=1.2.14,<2.0.0)
Requires-Dist: PyNaCl (>=1.5.0,<2.0.0)
Requires-Dist: PyYAML (>=6.0.2,<7.0.0)
Requires-Dist: algokit-utils (>=2.3.2,<3.0.0)
Requires-Dist: anyio (>=4.4.0,<5.0.0)
Requires-Dist: auto_mix_prep (>=0.2.0,<0.3.0)
Requires-Dist: certifi (>=2024.6.2,<2025.0.0)
Requires-Dist: cffi (>=1.16.0,<2.0.0)
Requires-Dist: h11 (>=0.14.0,<0.15.0)
Requires-Dist: httpcore (>=0.16.3,<0.17.0)
Requires-Dist: httpx (>=0.23.3,<0.24.0)
Requires-Dist: idna (>=3.7,<4.0)
Requires-Dist: msgpack (>=1.0.8,<2.0.0)
Requires-Dist: py-algorand-sdk (>=2.6.1,<3.0.0)
Requires-Dist: pycparser (>=2.22,<3.0)
Requires-Dist: pycryptodomex (>=3.20.0,<4.0.0)
Requires-Dist: python-dateutil (>=2.9.0.post0,<3.0.0)
Requires-Dist: python-dotenv (>=1.0.1,<2.0.0)
Requires-Dist: pytz (>=2024.1,<2025.0)
Requires-Dist: rfc3986 (>=1.5.0,<2.0.0)
Requires-Dist: setuptools (>=75.3.0,<76.0.0)
Requires-Dist: six (>=1.16.0,<2.0.0)
Requires-Dist: sniffio (>=1.3.1,<2.0.0)
Requires-Dist: typing_extensions (>=4.12.2,<5.0.0)
Requires-Dist: tzdata (>=2024.1,<2025.0)
Requires-Dist: wrapt (>=1.16.0,<2.0.0)
Project-URL: Repository, https://github.com/ValarStaking/valar/tree/master
